arx/__init__.py
arx/__main__.py
arx/__version__.py
arx-0.2.0.dist-info/COPYING
arx-0.2.0.dist-info/COPYING-GPL-3
arx-0.2.0.dist-info/METADATA
arx-0.2.0.dist-info/WHEEL
arx-0.2.0.dist-info/entry_points.txt
arx-0.2.0.dist-info/top_level.txt
arx-0.2.0.dist-info/RECORD
