Metadata-Version: 2.1
Name: arx
Version: 0.2.0
Summary: Simple data archiving tool
Home-page: https://git.ligo.org/jameson.rollins/arx
Author: Jameson Graef Rollins
Author-email: jameson.rollins@ligo.org
License: GPL-3.0-or-later
Classifier: License :: OSI Approved :: GNU General Public License v3 or later (GPLv3+)
Classifier: Development Status :: 5 - Production/Stable
Classifier: Natural Language :: English
Classifier: Operating System :: OS Independent
Classifier: Programming Language :: Python
License-File: COPYING
License-File: COPYING-GPL-3
Requires-Dist: pyyaml
